{
  "eventVersion": "1.08",
  "userIdentity": {
    "type": "Unknown",
    "accountId": "123456789012",
    "accessKeyId": "1d0e1b72-d0e0-4acb-9dbb-d65da93538b5"
  },
  "eventTime": "2023-03-26T17:06:29Z",
  "eventSource": "sso-directory.amazonaws.com",
  "eventName": "DisableUser",
  "awsRegion": "eu-west-1",
  "sourceIPAddress": "123.123.123.123",
  "userAgent": "PostmanRuntime/7.26.8",
  "requestParameters": {
    "identityStoreId": "d-93670dc30f",
    "userId": "22c554e4-c091-708a-0ec5-08b46733f1a2"
  },
  "responseElements": null,
  "requestID": "4e80363d-ab4c-4ff4-895a-97175d39cc50",
  "eventID": "d1678273-85cf-4a64-a14e-d0f58a35497a",
  "readOnly": false,
  "eventType": "AwsApiCall",
  "managementEvent": true,
  "recipientAccountId": "123456789012",
  "eventCategory": "Management",
  "tlsDetails": {
    "tlsVersion": "TLSv1.2",
    "cipherSuite": "ECDHE-RSA-AES128-GCM-SHA256",
    "clientProvidedHostHeader": "up.sso.eu-west-1.amazonaws.com"
  }
}
